co2_AT_emission/__init__.py
co2_AT_emission/emission_co2.py
co2_AT_emission-0.1.1.dist-info/METADATA
co2_AT_emission-0.1.1.dist-info/WHEEL
co2_AT_emission-0.1.1.dist-info/top_level.txt
co2_AT_emission-0.1.1.dist-info/RECORD
