Metadata-Version: 2.1
Name: co2-AT-emission
Version: 0.1.1
Summary: My first python library
Author: Raziuddin Khazi
Author-email: raziuddin.khazi@alexanderthamm.com
Requires-Dist: pytz (==2021.3)
Requires-Dist: eco2ai (==0.3.8)
